{
  "recipe": {
    "id": "citrixworkspace",
    "bundle": "Citrix Workspace.app",
    "identifier": "com.citrix.receiver.nomas",
    "download": "https://cdn-clients.anykeyit.ch/Static/CitrixWorkspaceApp_19.6.0.dmg",
    "sha256": "bd5dcf70e534731198eea7238aa206cd78e5ee01c599bb52befc90049ca23090",
    "appcast": {
      "url": null,
      "checkpoint": null
    },
    "version": "19.6.0",
    "build": null,
    "dir": "/Applications",
    "symlink": null,
    "web": "https://www.citrix.com/products/workspace-app/"
  }
}
